LICENSE
README.md
setup.cfg
setup.py
mcp_run_python_code.egg-info/PKG-INFO
mcp_run_python_code.egg-info/SOURCES.txt
mcp_run_python_code.egg-info/dependency_links.txt
mcp_run_python_code.egg-info/entry_points.txt
mcp_run_python_code.egg-info/not-zip-safe
mcp_run_python_code.egg-info/requires.txt
mcp_run_python_code.egg-info/top_level.txt
run_python_code/__init__.py
run_python_code/__main__.py
run_python_code/code.py
run_python_code/server.py
tests/test_code.py