Metadata-Version: 2.4
Name: mcp-run-python-code
Version: 0.0.2
Summary: mcp-run-python-code: MCP server for running Python code, installing packages, and executing Python files.
Home-page: https://github.com/shibing624/mcp-run-python-code
Author: XuMing
Author-email: xuming624@qq.com
License: Apache License 2.0
Keywords: python-interpreter,mcp,run-python-code,install-python-package,execute-python-file
Classifier: Intended Audience :: Developers
Classifier: Operating System :: OS Independent
Classifier: Natural Language :: Chinese (Simplified)
Classifier: Natural Language :: Chinese (Traditional)
Classifier: Programming Language :: Python
Classifier: Programming Language :: Python :: 3
Classifier: Topic :: Text Processing
Classifier: Topic :: Text Processing :: Indexing
Classifier: Topic :: Text Processing :: Linguistic
Requires-Python: >=3.10
License-File: LICENSE
Requires-Dist: mcp
Requires-Dist: requests
Requires-Dist: loguru
Dynamic: author
Dynamic: author-email
Dynamic: classifier
Dynamic: description
Dynamic: description-content-type
Dynamic: home-page
Dynamic: keywords
Dynamic: license
Dynamic: license-file
Dynamic: requires-dist
Dynamic: requires-python
Dynamic: summary
